{
  "recentFiles": [
    {
      "basename": "note",
      "path": "数学二/高等数学/基础/note.md"
    },
    {
      "basename": "2023-11-20",
      "path": "学习日报/Day/2023-11-20.md"
    },
    {
      "basename": "README",
      "path": "数学二/高等数学/基础/README.md"
    },
    {
      "basename": "read",
      "path": "Pub/Capture/read.md"
    },
    {
      "basename": "Tasks",
      "path": "Pub/Capture/Tasks.md"
    },
    {
      "basename": "2023-11-19",
      "path": "学习日报/Day/2023-11-19.md"
    },
    {
      "basename": "前期准备",
      "path": "前期准备/前期准备.md"
    },
    {
      "basename": "README",
      "path": "README.md"
    },
    {
      "basename": "微积分的本质--3Blue1Brown",
      "path": "数学二/高等数学/微积分的本质--3Blue1Brown.md"
    },
    {
      "basename": "2023-11-17",
      "path": "学习日报/Day/2023-11-17.md"
    },
    {
      "basename": "2023-11-16",
      "path": "学习日报/Day/2023-11-16.md"
    },
    {
      "basename": "Obsidian工作流",
      "path": "学习日报/Obsidian工作流.md"
    },
    {
      "basename": "线性代数的本质--3Blue1Brown",
      "path": "数学二/线性代数/线性代数的本质--3Blue1Brown.md"
    },
    {
      "basename": "2023-11-15",
      "path": "学习日报/Day/2023-11-15.md"
    },
    {
      "basename": "2023-11-14",
      "path": "学习日报/Day/2023-11-14.md"
    },
    {
      "basename": "Test-本地附件链接",
      "path": "Pub/PDF-Annotator/Test-本地附件链接.md"
    },
    {
      "basename": "Test-网络附件链接",
      "path": "Pub/PDF-Annotator/Test-网络附件链接.md"
    },
    {
      "basename": "2023-10-31",
      "path": "学习日报/Day/2023-10-31.md"
    },
    {
      "basename": "2023-10-28",
      "path": "学习日报/Day/2023-10-28.md"
    },
    {
      "basename": "2023-10-26",
      "path": "学习日报/Day/2023-10-26.md"
    }
  ],
  "omittedPaths": [],
  "maxLength": 20,
  "openType": "tab"
}